dsainone/__init__.py
dsainone/graph.py
dsainone/hash_table.py
dsainone/linked_list.py
dsainone/memory.py
dsainone/tree.py
dsainone-1.0.2.dist-info/LICENSE
dsainone-1.0.2.dist-info/METADATA
dsainone-1.0.2.dist-info/WHEEL
dsainone-1.0.2.dist-info/top_level.txt
dsainone-1.0.2.dist-info/RECORD
